biosimulators_xpp/__init__.py
biosimulators_xpp/__main__.py
biosimulators_xpp/_version.py
biosimulators_xpp/core.py
biosimulators_xpp/data_model.py
biosimulators_xpp/utils.py
biosimulators_xpp-0.0.13.dist-info/LICENSE
biosimulators_xpp-0.0.13.dist-info/METADATA
biosimulators_xpp-0.0.13.dist-info/WHEEL
biosimulators_xpp-0.0.13.dist-info/entry_points.txt
biosimulators_xpp-0.0.13.dist-info/top_level.txt
biosimulators_xpp-0.0.13.dist-info/RECORD
