Metadata-Version: 2.1
Name: biosimulators-xpp
Version: 0.0.13
Summary: BioSimulators-compliant command-line interface to the XPP simulation program.
Home-page: https://github.com/biosimulators/Biosimulators_XPP
Download-URL: https://github.com/biosimulators/Biosimulators_XPP
Author: BioSimulators Team
Author-email: info@biosimulators.org
License: MIT
Keywords: systems biology,computational biology,numerical simulation,BioSimulators,SBML,SED-ML,COMBINE,OMEX,XPP
Platform: UNKNOWN
Classifier: Development Status :: 3 - Alpha
Classifier: Intended Audience :: Science/Research
Classifier: License :: OSI Approved :: MIT License
Classifier: Topic :: Scientific/Engineering :: Bio-Informatics
License-File: LICENSE
Requires-Dist: biosimulators-utils[logging] (>=0.1.167)
Requires-Dist: kisao (>=2.28)
Requires-Dist: numpy
Requires-Dist: pandas
Provides-Extra: all
Requires-Dist: biosimulators-utils[containers] ; extra == 'all'
Requires-Dist: python-dateutil ; extra == 'all'
Requires-Dist: pyyaml ; extra == 'all'
Provides-Extra: docs
Provides-Extra: tests
Requires-Dist: biosimulators-utils[containers] ; extra == 'tests'
Requires-Dist: python-dateutil ; extra == 'tests'
Requires-Dist: pyyaml ; extra == 'tests'
